flasik/.DS_Store
flasik/__about__.py
flasik/__about__.pyc
flasik/__init__.py
flasik/__init__.pyc
flasik/cli.py
flasik/cli.pyc
flasik/commander.py
flasik/commander.pyc
flasik/core.py
flasik/core.pyc
flasik/decorators.pyc
flasik/exceptions.pyc
flasik/ext.pyc
flasik/extensions.py
flasik/extensions.pyc
flasik/flasik_db.py
flasik/flasik_db.pyc
flasik/functions.py
flasik/functions.pyc
flasik/plugins.py
flasik/plugins.pyc
flasik/render.pyc
flasik/request.py
flasik/request.pyc
flasik/response.py
flasik/response.pyc
flasik/signals.py
flasik/signals.pyc
flasik/utils.py
flasik/utils.pyc
flasik/__pycache__/__about__.cpython-36.pyc
flasik/__pycache__/__init__.cpython-36.pyc
flasik/__pycache__/cli.cpython-36.pyc
flasik/__pycache__/core.cpython-36.pyc
flasik/__pycache__/extensions.cpython-36.pyc
flasik/__pycache__/flasik_db.cpython-36.pyc
flasik/__pycache__/functions.cpython-36.pyc
flasik/__pycache__/plugins.cpython-36.pyc
flasik/__pycache__/request.cpython-36.pyc
flasik/__pycache__/response.cpython-36.pyc
flasik/__pycache__/signals.cpython-36.pyc
flasik/__pycache__/utils.cpython-36.pyc
flasik/plugins/.DS_Store
flasik/plugins/__init__.py
flasik/plugins/__init__.pyc
flasik/plugins/flasik_db.pyc
flasik/plugins/harambe_db.pyc
flasik/plugins/htmlcompress.py
flasik/plugins/htmlcompress.pyc
flasik/plugins/jade.pyc
flasik/plugins/jinja_helpers.pyc
flasik/plugins/logger.py
flasik/plugins/md.py
flasik/plugins/md.pyc
flasik/plugins/mocha_db.pyc
flasik/plugins/__pycache__/__init__.cpython-36.pyc
flasik/plugins/__pycache__/htmlcompress.cpython-36.pyc
flasik/scaffold/.DS_Store
flasik/scaffold/create-api-views/__init__.py
flasik/scaffold/create-api-views/__models__.py
flasik/scaffold/create-api-views/__views__.py
flasik/scaffold/create-template-views/.DS_Store
flasik/scaffold/create-template-views/__init__.py
flasik/scaffold/create-template-views/__models__.py
flasik/scaffold/create-template-views/__views__.py
flask_assembly-0.0.0.dist-info/METADATA
flask_assembly-0.0.0.dist-info/RECORD
flask_assembly-0.0.0.dist-info/WHEEL
flask_assembly-0.0.0.dist-info/entry_points.txt
flask_assembly-0.0.0.dist-info/top_level.txt
