Metadata-Version: 2.1
Name: flask-assembly
Version: 0.0.0
Summary: A mid stack Flask based framework that put structure in the file system. Features: Caching, Mailing, Storage, CSRF, recaptcha, Cors. Supports HTML and Markdown and more
Home-page: https://github.com/mardix/flask-assembly
Author: Mardix
Author-email: mcx2082@gmail.com
License: MIT
Keywords: flask,flasik,templates,views,classy,framework,mvc,blueprint
Platform: any
Classifier: Environment :: Web Environment
Classifier: Intended Audience :: Developers
Classifier: License :: OSI Approved :: BSD License
Classifier: Operating System :: OS Independent
Classifier: Programming Language :: Python
Classifier: Programming Language :: Python :: 2
Classifier: Programming Language :: Python :: 2.6
Classifier: Programming Language :: Python :: 2.7
Classifier: Programming Language :: Python :: 3
Classifier: Programming Language :: Python :: 3.3
Classifier: Programming Language :: Python :: 3.4
Classifier: Programming Language :: Python :: 3.5
Classifier: Topic :: Internet :: WWW/HTTP :: Dynamic Content
Classifier: Topic :: Software Development :: Libraries :: Python Modules
Requires-Dist: Flask (>=1.0.0)
Requires-Dist: Flask-Assets (==0.12)
Requires-Dist: cssmin (==0.2.0)
Requires-Dist: jsmin (==2.2.1)
Requires-Dist: flask-recaptcha (>=0.4.1)
Requires-Dist: flask-kvsession (==0.6.1)
Requires-Dist: flask-s3 (==0.3.1)
Requires-Dist: flask-mail (==0.9.0)
Requires-Dist: flask-caching (==1.0.0)
Requires-Dist: flask-cloudy (>=1.0.1)
Requires-Dist: flask-seasurf (==0.2.2)
Requires-Dist: flask-babel (==0.11.2)
Requires-Dist: flask-cors (>=3.0.8)
Requires-Dist: Active-Alchemy (>=1.0.0)
Requires-Dist: six (>=1.9.0)
Requires-Dist: passlib (<1.8.0,>=1.7.0)
Requires-Dist: bcrypt (==3.1.3)
Requires-Dist: python-slugify (==1.2.1)
Requires-Dist: humanize (==0.5.1)
Requires-Dist: redis (<3.0.0,>=2.10.0)
Requires-Dist: ses-mailer (>=0.13.0)
Requires-Dist: markdown (==2.6.2)
Requires-Dist: inflection (==0.3.1)
Requires-Dist: pyyaml (>=4.2b1)
Requires-Dist: click (==6.2)
Requires-Dist: sh (==1.11)
Requires-Dist: dicttoxml (==1.6.6)
Requires-Dist: arrow (==0.8.0)
Requires-Dist: blinker (==1.4)
Requires-Dist: itsdangerous (==0.24)
Requires-Dist: requests (>=2.13.0)
